deckian/__init__.py
deckian/__main__.py
deckian/chroot.py
deckian/data.py
deckian/disk.py
deckian-0.0.1.dist-info/LICENSE
deckian-0.0.1.dist-info/METADATA
deckian-0.0.1.dist-info/WHEEL
deckian-0.0.1.dist-info/entry_points.txt
deckian-0.0.1.dist-info/top_level.txt
deckian-0.0.1.dist-info/RECORD
