Metadata-Version: 2.1
Name: deckian
Version: 0.0.1
Summary: Dual-booting Debian on a Steam Deck, easily.
Author-email: hexaheximal <hexaheximal@proton.me>
License: GNU GENERAL PUBLIC LICENSE
Project-URL: Homepage, https://github.com/deckian/deckian
Keywords: linux,debian,steamdeck
Classifier: License :: OSI Approved :: GNU General Public License (GPL)
Classifier: Programming Language :: Python
Classifier: Programming Language :: Python :: 3
Requires-Python: >=3.7
License-File: LICENSE
